module_name/__init__.py
module_name/cli.py
module_name/resolve.py
module_name/test_resolve.py
module_name-0.6.0.dist-info/LICENSE.txt
module_name-0.6.0.dist-info/METADATA
module_name-0.6.0.dist-info/WHEEL
module_name-0.6.0.dist-info/entry_points.txt
module_name-0.6.0.dist-info/top_level.txt
module_name-0.6.0.dist-info/RECORD
