Metadata-Version: 2.1
Name: module_name
Version: 0.6.0
Summary: Simple Module to resolve module namespace
Home-page: https://github.com/dalejung/module_name
Download-URL: https://github.com/dalejung/module_name/tarball/0.6.0
Author: Dale Jung
Author-email: dale@dalejung.com
License: MIT
Classifier: Development Status :: 3 - Alpha
Classifier: Intended Audience :: Developers
Classifier: License :: OSI Approved :: MIT License
Classifier: Programming Language :: Python :: 2.7
Classifier: Programming Language :: Python :: 3
Classifier: Programming Language :: Python :: 3.3
Classifier: Programming Language :: Python :: 3.4
Classifier: Programming Language :: Python :: 3.5
License-File: LICENSE.txt
